auth_kit_fastapi/__init__.py
auth_kit_fastapi/api/__init__.py
auth_kit_fastapi/api/auth.py
auth_kit_fastapi/api/passkeys.py
auth_kit_fastapi/api/two_factor.py
auth_kit_fastapi/core/__init__.py
auth_kit_fastapi/core/app.py
auth_kit_fastapi/core/config.py
auth_kit_fastapi/core/database.py
auth_kit_fastapi/core/dependencies.py
auth_kit_fastapi/core/events.py
auth_kit_fastapi/core/security.py
auth_kit_fastapi/models/__init__.py
auth_kit_fastapi/models/user.py
auth_kit_fastapi/schemas/__init__.py
auth_kit_fastapi/schemas/auth.py
auth_kit_fastapi/schemas/passkey.py
auth_kit_fastapi/schemas/two_factor.py
auth_kit_fastapi/services/__init__.py
auth_kit_fastapi/services/email_service.py
auth_kit_fastapi/services/passkey_service.py
auth_kit_fastapi/services/two_factor_service.py
auth_kit_fastapi/services/user_service.py
tests/__init__.py
tests/conftest.py
tests/test_auth_endpoints.py
tests/test_passkey_endpoints.py
tests/test_services.py
tests/test_two_factor_endpoints.py
auth_kit_fastapi-0.3.19.dist-info/METADATA
auth_kit_fastapi-0.3.19.dist-info/WHEEL
auth_kit_fastapi-0.3.19.dist-info/top_level.txt
auth_kit_fastapi-0.3.19.dist-info/RECORD
