Metadata-Version: 2.1
Name: auth-kit-fastapi
Version: 0.3.19
Summary: FastAPI authentication backend for Auth Kit
Home-page: https://github.com/erickva/auth-kit
Author: Erick Ama
Author-email: me@erick.no
Classifier: Development Status :: 4 - Beta
Classifier: Intended Audience :: Developers
Classifier: Topic :: Software Development :: Libraries :: Python Modules
Classifier: License :: OSI Approved :: MIT License
Classifier: Programming Language :: Python :: 3
Classifier: Programming Language :: Python :: 3.8
Classifier: Programming Language :: Python :: 3.9
Classifier: Programming Language :: Python :: 3.10
Classifier: Programming Language :: Python :: 3.11
Classifier: Framework :: FastAPI
Requires-Python: >=3.8
Requires-Dist: fastapi>=0.100.0
Requires-Dist: sqlalchemy>=2.0.0
Requires-Dist: pydantic>=2.0.0
Requires-Dist: pydantic-settings>=2.0.0
Requires-Dist: python-jose[cryptography]>=3.3.0
Requires-Dist: passlib[bcrypt]>=1.7.4
Requires-Dist: python-multipart>=0.0.6
Requires-Dist: email-validator>=2.0.0
Requires-Dist: pyotp>=2.9.0
Requires-Dist: qrcode>=7.4.0
Requires-Dist: webauthn>=1.9.0
Requires-Dist: alembic>=1.12.0
Provides-Extra: dev
Requires-Dist: pytest>=7.0.0; extra == "dev"
Requires-Dist: pytest-asyncio>=0.21.0; extra == "dev"
Requires-Dist: httpx>=0.24.0; extra == "dev"
Requires-Dist: black>=23.0.0; extra == "dev"
Requires-Dist: flake8>=6.0.0; extra == "dev"
Requires-Dist: mypy>=1.0.0; extra == "dev"
Provides-Extra: mysql
Requires-Dist: pymysql>=1.1.0; extra == "mysql"
Provides-Extra: postgres
Requires-Dist: psycopg2-binary>=2.9.0; extra == "postgres"
Provides-Extra: redis
Requires-Dist: redis>=4.5.0; extra == "redis"
